janaf/__init__.py
janaf/_constant.py
janaf/_version.py
janaf/index.py
janaf/janaf.json
janaf/py.typed
janaf/table.py
janaf/data/Al-001.txt
janaf/data/Al-002.txt
janaf/data/Al-003.txt
janaf/data/Al-004.txt
janaf/data/Al-005.txt
janaf/data/Al-006.txt
janaf/data/Al-007.txt
janaf/data/Al-008.txt
janaf/data/Al-009.txt
janaf/data/Al-010.txt
janaf/data/Al-011.txt
janaf/data/Al-012.txt
janaf/data/Al-013.txt
janaf/data/Al-014.txt
janaf/data/Al-015.txt
janaf/data/Al-016.txt
janaf/data/Al-017.txt
janaf/data/Al-018.txt
janaf/data/Al-019.txt
janaf/data/Al-020.txt
janaf/data/Al-021.txt
janaf/data/Al-022.txt
janaf/data/Al-023.txt
janaf/data/Al-024.txt
janaf/data/Al-025.txt
janaf/data/Al-026.txt
janaf/data/Al-027.txt
janaf/data/Al-028.txt
janaf/data/Al-029.txt
janaf/data/Al-030.txt
janaf/data/Al-031.txt
janaf/data/Al-032.txt
janaf/data/Al-033.txt
janaf/data/Al-034.txt
janaf/data/Al-035.txt
janaf/data/Al-036.txt
janaf/data/Al-037.txt
janaf/data/Al-038.txt
janaf/data/Al-039.txt
janaf/data/Al-040.txt
janaf/data/Al-041.txt
janaf/data/Al-042.txt
janaf/data/Al-043.txt
janaf/data/Al-044.txt
janaf/data/Al-045.txt
janaf/data/Al-046.txt
janaf/data/Al-047.txt
janaf/data/Al-048.txt
janaf/data/Al-049.txt
janaf/data/Al-050.txt
janaf/data/Al-051.txt
janaf/data/Al-052.txt
janaf/data/Al-053.txt
janaf/data/Al-054.txt
janaf/data/Al-055.txt
janaf/data/Al-056.txt
janaf/data/Al-057.txt
janaf/data/Al-058.txt
janaf/data/Al-059.txt
janaf/data/Al-060.txt
janaf/data/Al-061.txt
janaf/data/Al-062.txt
janaf/data/Al-063.txt
janaf/data/Al-064.txt
janaf/data/Al-065.txt
janaf/data/Al-066.txt
janaf/data/Al-067.txt
janaf/data/Al-068.txt
janaf/data/Al-069.txt
janaf/data/Al-070.txt
janaf/data/Al-071.txt
janaf/data/Al-072.txt
janaf/data/Al-073.txt
janaf/data/Al-074.txt
janaf/data/Al-075.txt
janaf/data/Al-076.txt
janaf/data/Al-077.txt
janaf/data/Al-078.txt
janaf/data/Al-079.txt
janaf/data/Al-080.txt
janaf/data/Al-081.txt
janaf/data/Al-082.txt
janaf/data/Al-083.txt
janaf/data/Al-084.txt
janaf/data/Al-085.txt
janaf-1.2.0.dist-info/METADATA
janaf-1.2.0.dist-info/WHEEL
janaf-1.2.0.dist-info/licenses/LICENSE
janaf-1.2.0.dist-info/RECORD
