Metadata-Version: 2.4
Name: janaf
Version: 1.2.0
Summary: Python wrapper for NIST-JANAF Thermochemical Tables
Project-URL: Repository, https://github.com/n-takumasa/py-janaf
Author-email: Takumasa Nakamura <n.takumasa@gmail.com>
License-Expression: MIT
License-File: LICENSE
Classifier: Operating System :: OS Independent
Classifier: Programming Language :: Python
Classifier: Programming Language :: Python :: 3.8
Classifier: Programming Language :: Python :: 3.9
Classifier: Programming Language :: Python :: 3.10
Classifier: Programming Language :: Python :: 3.11
Classifier: Programming Language :: Python :: 3.12
Classifier: Programming Language :: Python :: 3.13
Classifier: Programming Language :: Python :: 3.14
Classifier: Programming Language :: Python :: Implementation :: CPython
Classifier: Topic :: Scientific/Engineering :: Chemistry
Classifier: Topic :: Scientific/Engineering :: Physics
Requires-Python: >=3.8
Requires-Dist: importlib-resources>=5.0; python_version < '3.9'
Requires-Dist: polars>=1.0.0
Provides-Extra: all
Requires-Dist: xarray>=2023.1.0; extra == 'all'
Provides-Extra: xarray
Requires-Dist: xarray>=2023.1.0; extra == 'xarray'
